django_drf_dynamics/__init__.py
django_drf_dynamics/admin.py
django_drf_dynamics/apps.py
django_drf_dynamics/models.py
django_drf_dynamics/renderers.py
django_drf_dynamics/tests.py
django_drf_dynamics/_utils/__init__.py
django_drf_dynamics/_utils/dynamic_filters.py
django_drf_dynamics/_utils/dynamic_forms.py
django_drf_dynamics/autocomplete/__init__.py
django_drf_dynamics/autocomplete/advanced_autocomplete.py
django_drf_dynamics/autocomplete/autocomplete_backends.py
django_drf_dynamics/autocomplete/autocomplete_serializers.py
django_drf_dynamics/filters/__init__.py
django_drf_dynamics/filters/advanced_filters.py
django_drf_dynamics/filters/date_filters.py
django_drf_dynamics/filters/dynamic_filters.py
django_drf_dynamics/filters/range_filters.py
django_drf_dynamics/lists/__init__.py
django_drf_dynamics/lists/dynamic_lists.py
django_drf_dynamics/lists/list_backends.py
django_drf_dynamics/lists/list_serializers.py
django_drf_dynamics/serializers/__init__.py
django_drf_dynamics/serializers/defaults.py
django_drf_dynamics/serializers/dynamic_serializers.py
django_drf_dynamics/serializers/fields.py
django_drf_dynamics/serializers/serializers_mixins.py
django_drf_dynamics/views/__init__.py
django_drf_dynamics/views/dsl_views_mixins.py
django_drf_dynamics/views/views_mixins.py
django_drf_dynamics-0.0.11.dist-info/licenses/LICENSE
django_drf_dynamics-0.0.11.dist-info/METADATA
django_drf_dynamics-0.0.11.dist-info/WHEEL
django_drf_dynamics-0.0.11.dist-info/top_level.txt
django_drf_dynamics-0.0.11.dist-info/RECORD
