Metadata-Version: 2.4
Name: django-drf-dynamics
Version: 0.0.11
Summary: A Django app for restframework dynamic components.
Author-email: Pierre-Claver Koko Banywerha <pierreclaverkoko@gmail.com>
Project-URL: Homepage, https://github.com/pierreclaverkoko/django-drf-dynamics
Classifier: Environment :: Web Environment
Classifier: Framework :: Django
Classifier: Intended Audience :: Developers
Classifier: Operating System :: OS Independent
Classifier: Programming Language :: Python
Classifier: Programming Language :: Python :: 3
Classifier: Programming Language :: Python :: 3 :: Only
Classifier: Programming Language :: Python :: 3.10
Classifier: Programming Language :: Python :: 3.11
Classifier: Programming Language :: Python :: 3.12
Classifier: Programming Language :: Python :: 3.13
Classifier: Topic :: Internet :: WWW/HTTP
Classifier: Topic :: Internet :: WWW/HTTP :: Dynamic Content
Requires-Python: >=3.10
License-File: LICENSE
Requires-Dist: django>=4.2
Requires-Dist: django-filter>=25.1
Dynamic: license-file
